biograph/__init__.py
BioGraph-0.0.1.dist-info/LICENSE
BioGraph-0.0.1.dist-info/METADATA
BioGraph-0.0.1.dist-info/WHEEL
BioGraph-0.0.1.dist-info/top_level.txt
BioGraph-0.0.1.dist-info/RECORD
